metasdk/__init__.py
metasdk/__state.py
metasdk/apiclient.py
metasdk/event_bus.py
metasdk/exceptions.py
metasdk/info.py
metasdk/internal.py
metasdk/utils.py
metasdk/worker.py
metasdk/logger/__init__.py
metasdk/logger/bulk_logger.py
metasdk/logger/logger.py
metasdk/schemas/IssueSchema.py
metasdk/schemas/__init__.py
metasdk/services/ApiProxyService.py
metasdk/services/AsyncDbQueryService.py
metasdk/services/AuthService.py
metasdk/services/CacheService.py
metasdk/services/DbQueryService.py
metasdk/services/DbService.py
metasdk/services/DevService.py
metasdk/services/ExportService.py
metasdk/services/ExternalSystemService.py
metasdk/services/FeedService.py
metasdk/services/IssueService.py
metasdk/services/LockService.py
metasdk/services/MailService.py
metasdk/services/MediaService.py
metasdk/services/MetaqlService.py
metasdk/services/ObjectLogService.py
metasdk/services/SettingsService.py
metasdk/services/StarterService.py
metasdk/services/UserManagementService.py
metasdk/services/__init__.py
metasdk/tools/__init__.py
metasdk/tools/extract_event_handlers.py
metasdk/tools/parsers.py
metasdk/tools/validators.py
metasdk/tools/wrappers.py
metasdk/transport/__init__.py
metasdk/transport/async_http.py
metasdk-1.11.2.dist-info/LICENSE
metasdk-1.11.2.dist-info/METADATA
metasdk-1.11.2.dist-info/WHEEL
metasdk-1.11.2.dist-info/top_level.txt
metasdk-1.11.2.dist-info/RECORD
