Metadata-Version: 2.1
Name: metasdk
Version: 1.11.2
Summary: Devision Meta SDK
Home-page: https://github.com/devision-io/metasdk
Author: Artur Geraschenko
Author-email: arturgspb@gmail.com
License: MIT
Classifier: Programming Language :: Python :: 3
License-File: LICENSE
Requires-Dist: six (<2.0.0,>=1.16.0)
Requires-Dist: python-logstash (<1.0.0,>=0.4.8)
Requires-Dist: fluent-logger (<1.0.0,>=0.11.0)
Requires-Dist: PyJWT (<3.0.0,>=2.8.0)
Requires-Dist: requests (<3.0.0,>=2.31.0)
Requires-Dist: httpx (<1.0.0,>=0.27.0)
Requires-Dist: redis (<6.0.0,>=5.0.4)
Requires-Dist: sqlparse (<1.0.0,>=0.4.4)
Requires-Dist: pytest (<9.0.0,>=8.2.1)
Requires-Dist: pytest-mock (<4.0.0,>=3.14.0)
Requires-Dist: pytest-asyncio (<2.0.0,>=1.0.0)
